rjpo/__init__.py
rjpo/cg.py
rjpo/rjpo.py
rjpo/util.py
rjpo-0.0.1.dist-info/LICENSE
rjpo-0.0.1.dist-info/METADATA
rjpo-0.0.1.dist-info/WHEEL
rjpo-0.0.1.dist-info/top_level.txt
rjpo-0.0.1.dist-info/RECORD
