Metadata-Version: 2.1
Name: rjpo
Version: 0.0.1
Summary: An implementation of a reversible jump perturbation optimization (RJPO) method for sampling high-dimensional Gaussians.
Author: Jonathan Lindbloom
Author-email: Jonathan Lindbloom <jonathan@lindbloom.com>
License: LICENSE
Project-URL: Homepage, https://github.com/jlindbloom/rjpo-gaussian-sampling
Project-URL: Bug Tracker, https://github.com/jlindbloom/rjpo-gaussian-sampling/issues
Keywords: gaussian sampling
Classifier: Programming Language :: Python :: 3
Classifier: License :: OSI Approved :: MIT License
Classifier: Operating System :: OS Independent
Classifier: Topic :: Scientific/Engineering :: Mathematics
Requires-Python: >=3.7
License-File: LICENSE
